LICENSE
MANIFEST.in
README.rst
pytest_report_stream.py
setup.py
pytest_report_stream.egg-info/PKG-INFO
pytest_report_stream.egg-info/SOURCES.txt
pytest_report_stream.egg-info/dependency_links.txt
pytest_report_stream.egg-info/entry_points.txt
pytest_report_stream.egg-info/requires.txt
pytest_report_stream.egg-info/top_level.txt
tests/test_report_stream.py