Metadata-Version: 2.1
Name: pytest-report-stream
Version: 0.1.0
Summary:          A pytest plugin which allows to stream test reports at runtime     
Home-page: https://github.com/kolitiri/pytest-report-stream
Author: Christos Liontos
Author-email: christos.liontos.pr@gmail.com
Maintainer: Christos Liontos
Maintainer-email: christos.liontos.pr@gmail.com
License: MIT
Platform: UNKNOWN
Classifier: Development Status :: 4 - Beta
Classifier: Framework :: Pytest
Classifier: Intended Audience :: Developers
Classifier: Topic :: Software Development :: Testing
Classifier: Programming Language :: Python
Classifier: Programming Language :: Python :: 3
Classifier: Programming Language :: Python :: 3.9
Classifier: Programming Language :: Python :: 3.10
Classifier: Programming Language :: Python :: 3.11
Classifier: Programming Language :: Python :: 3.12
Classifier: Programming Language :: Python :: 3 :: Only
Classifier: Programming Language :: Python :: Implementation :: CPython
Classifier: Programming Language :: Python :: Implementation :: PyPy
Classifier: Operating System :: OS Independent
Classifier: License :: OSI Approved :: MIT License
Requires-Python: >=3.9
License-File: LICENSE
